{  
   "app":{  
      "nodes":[  
         {  
            "id":7252,
            "name":"app-1",
            "fullName":"tenant-1/app-1",
            "type":"app",
            "uiData":{  
               "x":500.0,
               "y":50.0
            },
            "noOfInstances":1,
            "pKey":7252
         },
         {  
            "id":7254,
            "name":"DBTIER",
            "fullName":"tenant-1/DBTIER",
            "type":"epg",
            "uiData":{  
               "x":320.0,
               "y":190.0
            },
            "noOfEndPoints":25,
            "span":2,
            "epgSubnets":1,
            "bdId":7253,
            "bdName":"tenant-1/BDapp-1-0",
            "sharedServicesEnabled":true,
            "sharedServiceId":5,
            "sharedServiceName":"Common/SHARED1",
            "noOfsharedServiceFilter":4,
            "ports":0,
            "appId":7252,
            "noOfInstances":1,
            "pKey":7254
         },
         {  
            "id":7258,
            "name":"epg-1",
            "fullName":"tenant-1/epg-1",
            "type":"epg",
            "uiData":{  
               "x":440.0,
               "y":190.0
            },
            "noOfEndPoints":20,
            "span":2,
            "epgSubnets":0,
            "bdId":7246,
            "bdName":"tenant-1/BDapp-1",
            "sharedServicesEnabled":true,
            "sharedServiceId":5,
            "sharedServiceName":"Common/SHARED1",
            "noOfsharedServiceFilter":1,
            "ports":0,
            "appId":7252,
            "noOfInstances":1,
            "pKey":7258
         },
         {  
            "id":7255,
            "name":"APPTIER",
            "fullName":"tenant-1/APPTIER",
            "type":"epg",
            "uiData":{  
               "x":560.0,
               "y":190.0
            },
            "noOfEndPoints":25,
            "span":2,
            "epgSubnets":1,
            "bdId":7253,
            "bdName":"tenant-1/BDapp-1-0",
            "sharedServicesEnabled":true,
            "sharedServiceId":5,
            "sharedServiceName":"Common/SHARED1",
            "noOfsharedServiceFilter":4,
            "ports":0,
            "appId":7252,
            "noOfInstances":1,
            "pKey":7255
         },
         {  
            "id":7259,
            "name":"epg-2",
            "fullName":"tenant-1/epg-2",
            "type":"epg",
            "uiData":{  
               "x":680.0,
               "y":190.0
            },
            "noOfEndPoints":20,
            "span":2,
            "epgSubnets":0,
            "bdId":7246,
            "bdName":"tenant-1/BDapp-1",
            "sharedServicesEnabled":true,
            "sharedServiceId":5,
            "sharedServiceName":"Common/SHARED1",
            "noOfsharedServiceFilter":1,
            "ports":0,
            "appId":7252,
            "noOfInstances":1,
            "pKey":7259
         },
         {  
            "id":7257,
            "name":"ctL3OUT",
            "fullName":"tenant-1/ctL3OUT",
            "type":"contractl3",
            "uiData":{  
               "x":320.0,
               "y":330.0
            },
            "noOfFilters":1,
            "providerEnforced":false,
            "consumerEnforced":false,
            "providerId":7255,
            "consumerId":7244,
            "providerType":"epg",
            "consumerType":"l3out",
            "providerName":"tenant-1/APPTIER",
            "consumerName":"tenant-1/LocalL3OUT",
            "noOfInstances":1,
            "pKey":7257
         },
         {  
            "id":7256,
            "name":"ctDBAPP",
            "fullName":"tenant-1/ctDBAPP",
            "type":"contract",
            "uiData":{  
               "x":440.0,
               "y":330.0
            },
            "noOfFilters":4,
            "providerEnforced":true,
            "consumerEnforced":false,
            "providerId":7254,
            "consumerId":7255,
            "providerType":"epg",
            "consumerType":"epg",
            "providerName":"tenant-1/DBTIER",
            "consumerName":"tenant-1/APPTIER",
            "noOfInstances":1,
            "pKey":7256
         },
         {  
            "id":7261,
            "name":"contract-2",
            "fullName":"tenant-1/contract-2",
            "type":"contract",
            "uiData":{  
               "x":560.0,
               "y":330.0
            },
            "noOfFilters":1,
            "providerEnforced":true,
            "consumerEnforced":false,
            "providerId":7258,
            "consumerId":7259,
            "providerType":"epg",
            "consumerType":"epg",
            "providerName":"tenant-1/epg-1",
            "consumerName":"tenant-1/epg-2",
            "noOfInstances":1,
            "pKey":7261
         },
         {  
            "id":7260,
            "name":"contract-1",
            "fullName":"tenant-1/contract-1",
            "type":"contract",
            "uiData":{  
               "x":680.0,
               "y":330.0
            },
            "noOfFilters":1,
            "providerEnforced":true,
            "consumerEnforced":false,
            "providerId":7255,
            "consumerId":7259,
            "providerType":"epg",
            "consumerType":"epg",
            "providerName":"tenant-1/APPTIER",
            "consumerName":"tenant-1/epg-2",
            "noOfInstances":1,
            "pKey":7260
         }
      ],
      "connections":[  
         {  
            "id":2882,
            "dataItem":{  
               "from":"7252",
               "to":"7254"
            }
         },
         {  
            "id":6385,
            "dataItem":{  
               "from":"7252",
               "to":"7258"
            }
         },
         {  
            "id":5359,
            "dataItem":{  
               "from":"7252",
               "to":"7255"
            }
         },
         {  
            "id":3580,
            "dataItem":{  
               "from":"7252",
               "to":"7259"
            }
         },
         {  
            "id":3959,
            "dataItem":{  
               "from":"7255",
               "to":"7257"
            }
         },
         {  
            "id":3948,
            "dataItem":{  
               "from":"7255",
               "to":"7256"
            }
         },
         {  
            "id":6757,
            "dataItem":{  
               "from":"7254",
               "to":"7256"
            }
         },
         {  
            "id":4319,
            "dataItem":{  
               "from":"7259",
               "to":"7261"
            }
         },
         {  
            "id":5368,
            "dataItem":{  
               "from":"7258",
               "to":"7261"
            }
         },
         {  
            "id":3995,
            "dataItem":{  
               "from":"7259",
               "to":"7260"
            }
         },
         {  
            "id":6593,
            "dataItem":{  
               "from":"7255",
               "to":"7260"
            }
         }
      ]
   },
   "fabric":{  
      "nodes":[  

      ],
      "connections":[  

      ]
   }
}